MANIFEST.in
README.md
setup.py
django_swift/__init__.py
django_swift/storage.py
django_swift/views.py
django_swift.egg-info/PKG-INFO
django_swift.egg-info/SOURCES.txt
django_swift.egg-info/dependency_links.txt
django_swift.egg-info/requires.txt
django_swift.egg-info/top_level.txt