Metadata-Version: 1.1
Name: django-swift
Version: 0.9.3
Summary: a django storage for swift
Home-page: https://github.com/duanhongyi/django_swift/
Author: duanhongyi
Author-email: duanhongyi@doopai.com
License: BSD
Platform: UNKNOWN
Classifier: Development Status :: 5 - Production/Stable
Classifier: Environment :: Web Environment
Classifier: Intended Audience :: Developers
Classifier: License :: OSI Approved :: BSD License
Classifier: Operating System :: OS Independent
Classifier: Programming Language :: Python
Classifier: Framework :: Django
